{
  "date": {
    "precision": 1.0,
    "recall": 1.0,
    "f1-score": 1.0,
    "support": 7,
    "confused_with": {}
  },
  "price": {
    "precision": 1.0,
    "recall": 1.0,
    "f1-score": 1.0,
    "support": 30,
    "confused_with": {}
  },
  "service_ask": {
    "precision": 1.0,
    "recall": 1.0,
    "f1-score": 1.0,
    "support": 26,
    "confused_with": {}
  },
  "phone": {
    "precision": 0.8571428571428571,
    "recall": 1.0,
    "f1-score": 0.923076923076923,
    "support": 6,
    "confused_with": {}
  },
  "customer": {
    "precision": 1.0,
    "recall": 0.8461538461538461,
    "f1-score": 0.9166666666666666,
    "support": 13,
    "confused_with": {
      "dentist": 2
    }
  },
  "dentist": {
    "precision": 0.0,
    "recall": 0.0,
    "f1-score": 0.0,
    "support": 3,
    "confused_with": {}
  },
  "address": {
    "precision": 1.0,
    "recall": 1.0,
    "f1-score": 1.0,
    "support": 15,
    "confused_with": {}
  },
  "email": {
    "precision": 1.0,
    "recall": 1.0,
    "f1-score": 1.0,
    "support": 4,
    "confused_with": {}
  },
  "note": {
    "precision": 0.0,
    "recall": 0.0,
    "f1-score": 0.0,
    "support": 10,
    "confused_with": {}
  },
  "service": {
    "precision": 0.8,
    "recall": 0.6666666666666666,
    "f1-score": 0.7272727272727272,
    "support": 12,
    "confused_with": {}
  },
  "gender": {
    "precision": 0.0,
    "recall": 0.0,
    "f1-score": 0.0,
    "support": 1,
    "confused_with": {}
  },
  "timetodo": {
    "precision": 1.0,
    "recall": 1.0,
    "f1-score": 1.0,
    "support": 28,
    "confused_with": {}
  },
  "micro avg": {
    "precision": 0.9507042253521126,
    "recall": 0.8709677419354839,
    "f1-score": 0.9090909090909091,
    "support": 155
  },
  "macro avg": {
    "precision": 0.7214285714285715,
    "recall": 0.7094017094017095,
    "f1-score": 0.7139180264180265,
    "support": 155
  },
  "weighted avg": {
    "precision": 0.8886635944700461,
    "recall": 0.8709677419354839,
    "f1-score": 0.8785961350477479,
    "support": 155
  }
}