[
  {
    "text": "có thể tôi đến trễ xíu",
    "entities": [
      {
        "start": 0,
        "end": 22,
        "value": "có thể tôi đến trễ xíu",
        "entity": "note"
      }
    ],
    "predicted_entities": []
  },
  {
    "text": "ko",
    "entities": [
      {
        "start": 0,
        "end": 2,
        "value": "ko",
        "entity": "note"
      }
    ],
    "predicted_entities": []
  },
  {
    "text": "ông nội",
    "entities": [
      {
        "start": 0,
        "end": 7,
        "value": "ông nội",
        "entity": "gender"
      }
    ],
    "predicted_entities": []
  },
  {
    "text": "có",
    "entities": [],
    "predicted_entities": [
      {
        "entity": "note",
        "start": 0,
        "end": 2,
        "confidence_entity": 0.6039937734603882,
        "value": "có",
        "extractor": "DIETClassifier"
      }
    ]
  },
  {
    "text": "ai cũng được",
    "entities": [
      {
        "start": 0,
        "end": 12,
        "value": "ai cũng được",
        "entity": "dentist"
      }
    ],
    "predicted_entities": []
  },
  {
    "text": "nam",
    "entities": [
      {
        "start": 0,
        "end": 3,
        "value": "nam",
        "entity": "customer"
      }
    ],
    "predicted_entities": []
  }
]