{
  "date": {
    "precision": 1.0,
    "recall": 1.0,
    "f1-score": 1.0,
    "support": 7,
    "confused_with": {}
  },
  "price": {
    "precision": 1.0,
    "recall": 1.0,
    "f1-score": 1.0,
    "support": 22,
    "confused_with": {}
  },
  "service_ask": {
    "precision": 1.0,
    "recall": 1.0,
    "f1-score": 1.0,
    "support": 17,
    "confused_with": {}
  },
  "phone": {
    "precision": 1.0,
    "recall": 1.0,
    "f1-score": 1.0,
    "support": 6,
    "confused_with": {}
  },
  "customer": {
    "precision": 0.7777777777777778,
    "recall": 0.5384615384615384,
    "f1-score": 0.6363636363636364,
    "support": 13,
    "confused_with": {}
  },
  "dentist": {
    "precision": 1.0,
    "recall": 0.5,
    "f1-score": 0.6666666666666666,
    "support": 4,
    "confused_with": {
      "customer": 2
    }
  },
  "address": {
    "precision": 1.0,
    "recall": 1.0,
    "f1-score": 1.0,
    "support": 15,
    "confused_with": {}
  },
  "email": {
    "precision": 1.0,
    "recall": 1.0,
    "f1-score": 1.0,
    "support": 4,
    "confused_with": {}
  },
  "note": {
    "precision": 1.0,
    "recall": 0.125,
    "f1-score": 0.2222222222222222,
    "support": 8,
    "confused_with": {}
  },
  "service": {
    "precision": 0.7692307692307693,
    "recall": 1.0,
    "f1-score": 0.8695652173913044,
    "support": 10,
    "confused_with": {}
  },
  "gender": {
    "precision": 0.0,
    "recall": 0.0,
    "f1-score": 0.0,
    "support": 2,
    "confused_with": {}
  },
  "timetodo": {
    "precision": 1.0,
    "recall": 1.0,
    "f1-score": 1.0,
    "support": 25,
    "confused_with": {}
  },
  "micro avg": {
    "precision": 0.943089430894309,
    "recall": 0.8721804511278195,
    "f1-score": 0.90625,
    "support": 133
  },
  "macro avg": {
    "precision": 0.8789173789173791,
    "recall": 0.7636217948717948,
    "f1-score": 0.7829014785536524,
    "support": 133
  },
  "weighted avg": {
    "precision": 0.9458903669429986,
    "recall": 0.8721804511278195,
    "f1-score": 0.8828031871510132,
    "support": 133
  }
}